documenter/__init__.py
documenter/__main__.py
documenter-0.1.0.dist-info/licenses/LICENSE
documenter-0.1.0.dist-info/METADATA
documenter-0.1.0.dist-info/WHEEL
documenter-0.1.0.dist-info/entry_points.txt
documenter-0.1.0.dist-info/top_level.txt
documenter-0.1.0.dist-info/RECORD
