Metadata-Version: 2.4
Name: documenter
Version: 0.1.0
Summary: Easy to load a markdown document and show it.
Home-page: https://github.com/xystudio889/documenter
Author: xystudio
Author-email: xystudio <173288240@qq.com>
License: MIT License
Keywords: load document,document,documenter,markdown
Classifier: Programming Language :: Python :: 3
Classifier: License :: OSI Approved :: MIT License
Classifier: Operating System :: OS Independent
Requires-Python: >=3.6
License-File: LICENSE
Provides-Extra: dev
Dynamic: author
Dynamic: home-page
Dynamic: license-file
Dynamic: requires-python
